rapyuta/__init__.py
rapyuta/arrays.py
rapyuta/astrom.py
rapyuta/calib.py
rapyuta/imaging.py
rapyuta/inout.py
rapyuta/maths.py
rapyuta/plots.py
rapyuta/utilities.py
rapyuta/lib/data/caliberr.h5
rapyuta/lib/data/filt_2MASS1.h5
rapyuta/lib/data/filt_2MASS2.h5
rapyuta/lib/data/filt_2MASS3.h5
rapyuta/lib/data/filt_AKARI_FIS1.h5
rapyuta/lib/data/filt_AKARI_FIS2.h5
rapyuta/lib/data/filt_AKARI_FIS3.h5
rapyuta/lib/data/filt_AKARI_FIS4.h5
rapyuta/lib/data/filt_AKARI_IRC1.h5
rapyuta/lib/data/filt_AKARI_IRC2.h5
rapyuta/lib/data/filt_AKARI_IRC3.h5
rapyuta/lib/data/filt_AKARI_IRC4.h5
rapyuta/lib/data/filt_AKARI_IRC5.h5
rapyuta/lib/data/filt_AKARI_IRC6.h5
rapyuta/lib/data/filt_AKARI_IRC7.h5
rapyuta/lib/data/filt_AKARI_IRC8.h5
rapyuta/lib/data/filt_AKARI_IRC9.h5
rapyuta/lib/data/filt_DIRBE1.h5
rapyuta/lib/data/filt_DIRBE10.h5
rapyuta/lib/data/filt_DIRBE2.h5
rapyuta/lib/data/filt_DIRBE3.h5
rapyuta/lib/data/filt_DIRBE4.h5
rapyuta/lib/data/filt_DIRBE5.h5
rapyuta/lib/data/filt_DIRBE6.h5
rapyuta/lib/data/filt_DIRBE7.h5
rapyuta/lib/data/filt_DIRBE8.h5
rapyuta/lib/data/filt_DIRBE9.h5
rapyuta/lib/data/filt_HFI1.h5
rapyuta/lib/data/filt_HFI2.h5
rapyuta/lib/data/filt_HFI3.h5
rapyuta/lib/data/filt_HFI4.h5
rapyuta/lib/data/filt_HFI5.h5
rapyuta/lib/data/filt_HFI6.h5
rapyuta/lib/data/filt_IRAC1.h5
rapyuta/lib/data/filt_IRAC2.h5
rapyuta/lib/data/filt_IRAC3.h5
rapyuta/lib/data/filt_IRAC4.h5
rapyuta/lib/data/filt_IRAS1.h5
rapyuta/lib/data/filt_IRAS2.h5
rapyuta/lib/data/filt_IRAS3.h5
rapyuta/lib/data/filt_IRAS4.h5
rapyuta/lib/data/filt_LFI1.h5
rapyuta/lib/data/filt_LFI2.h5
rapyuta/lib/data/filt_LFI3.h5
rapyuta/lib/data/filt_MIPS1.h5
rapyuta/lib/data/filt_MIPS2.h5
rapyuta/lib/data/filt_MIPS3.h5
rapyuta/lib/data/filt_MSX1.h5
rapyuta/lib/data/filt_MSX2.h5
rapyuta/lib/data/filt_MSX3.h5
rapyuta/lib/data/filt_MSX4.h5
rapyuta/lib/data/filt_PACS1.h5
rapyuta/lib/data/filt_PACS2.h5
rapyuta/lib/data/filt_PACS3.h5
rapyuta/lib/data/filt_SPIRE1.h5
rapyuta/lib/data/filt_SPIRE2.h5
rapyuta/lib/data/filt_SPIRE3.h5
rapyuta-2.2.1.dist-info/LICENSE
rapyuta-2.2.1.dist-info/METADATA
rapyuta-2.2.1.dist-info/WHEEL
rapyuta-2.2.1.dist-info/entry_points.txt
rapyuta-2.2.1.dist-info/top_level.txt
rapyuta-2.2.1.dist-info/RECORD
