Metadata-Version: 2.1
Name: rapyuta
Version: 2.2.1
Summary: libraRy of Astronomical PYthon UTilities for Astrophysics nerds
Home-page: https://github.com/kxxdhdn/RAPYUTA
Author: D. HU
Author-email: dangning.hu@outlook.com
License: BSD
Project-URL: IDL, https://github.com/kxxdhdn/RAPYUTA/tree/main/idl
Project-URL: SwING, https://github.com/kxxdhdn/RAPYUTA/tree/main/swing
Project-URL: Tests, https://github.com/kxxdhdn/RAPYUTA/tree/main/tests
Keywords: astronomy astrophysics astrometry imaging spectroscopy spitzer akari jwst
Platform: UNKNOWN
Classifier: Programming Language :: Python :: 3
Classifier: License :: OSI Approved :: BSD License
Classifier: Operating System :: OS Independent
Requires-Python: >=3.6
License-File: LICENSE
Requires-Dist: numpy
Requires-Dist: scipy
Requires-Dist: matplotlib
Requires-Dist: astropy
Requires-Dist: reproject (>=0.7.1)
Requires-Dist: h5py
Requires-Dist: tqdm
